youtyper/__init__.py
youtyper/__main__.py
youtyper/logs.py
youtyper/main.py
youtyper/ui.py
youtyper/analyzers/__init__.py
youtyper/analyzers/analyzer.py
youtyper/analyzers/built_in.py
youtyper/assets/__init__.py
youtyper/assets/common_english_6_grams.txt
youtyper/assets/famous_texts.py
youtyper/assets/pangrams.txt
youtyper/assets/universal_declaration_of_human_rights.txt
youtyper/lessons/__init__.py
youtyper/lessons/built_in.py
youtyper/lessons/lessons.py
youtyper-0.1.0.dist-info/METADATA
youtyper-0.1.0.dist-info/WHEEL
youtyper-0.1.0.dist-info/entry_points.txt
youtyper-0.1.0.dist-info/top_level.txt
youtyper-0.1.0.dist-info/RECORD
