Metadata-Version: 2.1
Name: youtyper
Version: 0.1.0
Summary: A customizable command line touch typing tutor
Home-page: http://github.com/hmirin/youtyper
Author: hmirin
License: UNKNOWN
Keywords: touch-typing typing
Platform: UNKNOWN
Classifier: Development Status :: 3 - Alpha
Classifier: Environment :: Console :: Curses
Classifier: Intended Audience :: Developers
Classifier: Intended Audience :: Education
Classifier: Intended Audience :: End Users/Desktop
Classifier: Natural Language :: English
Classifier: Programming Language :: Python :: 3.8
Classifier: Topic :: Utilities
Classifier: Topic :: Education
Requires-Python: >=3.8
Requires-Dist: click (>=7)
Provides-Extra: dev
Requires-Dist: nose ; extra == 'dev'
Requires-Dist: coverage ; extra == 'dev'
